proy/posoco2000.v


module posoco2000(
    input clk,
    output reg [9:0] sel,
    output reg [7:0] segm
    );
wire [3:0] cont;
contador dut(
.clk(clk),
.count(cont)
);

always@(posedge clk)
begin
    if(cont==4'b0000)
    begin
    //p
        sel=10'b0000000001;
        segm=8'b11001110;
    end

    if(cont==4'b0001)
    begin
    //o    
        sel=10'b0000000010;
        segm=8'b11111100;
    end

    if(cont==4'b0010)
    begin
    //s    
        sel=10'b0000000100;
        segm=8'b10110110;
    end

    if(cont==4'b0011)
    begin
    //o    
        sel=10'b0000001000;
        segm=8'b11111100;
    end

    if(cont==4'b0100)
    begin
    //c    
        sel=10'b0000010000;
        segm=8'b10011100;
    end

    if(cont==4'b0101)
    begin
    //o    
        sel=10'b0000100000;
        segm=8'b11111100;
    end

    if(cont==4'b0110)
    begin
    //2    
        sel=10'b0001000000;
        segm=8'b11011010;
    end 

    if(cont==4'b0111)
    begin
    //0    
        sel=10'b0010000000;
        segm=8'b11111100;
    end 

    if(cont==4'b1000)
    begin
    //0    
        sel=10'b0100000000;
        segm=8'b11111100;
    end

    if(cont==4'b1001)
    begin
    //0    
        sel=10'b1000000000;
        segm=8'b11111100;
    end
end
endmodule

module contador(count,clk);
    output [3:0] count;
    input  clk;
    
    reg [3:0] count=0;
    always @(posedge clk)
        if(count==4'd9)
            count<=4'b0;
        else
        count <= count + 1'b1;
endmodule

proy/posoco2000_tb.v
module posoco2000_tb;
    reg clk=0;
    wire [9:0] sel;
    wire [7:0] segm;

    
    posoco2000 dut(
    .clk(clk),
    .sel(sel),
    .segm(segm)
    );

   
initial
begin 
 
$dumpfile("posoco2000.vcd");
$dumpvars(0,posoco2000_tb);
end 

initial 
repeat (200) begin	
    #10
    clk = ~clk; 

end

endmodule

proy/posoco2000.vcd
$date
	Thu Oct 26 16:13:58 2023
$end
$version
	Icarus Verilog
$end
$timescale
	1s
$end
$scope module posoco2000_tb $end
$var wire 10 ! sel [9:0] $end
$var wire 8 " segm [7:0] $end
$var reg 1 # clk $end
$scope module dut $end
$var wire 1 # clk $end
$var wire 4 $ cont [3:0] $end
$var reg 8 % segm [7:0] $end
$var reg 10 & sel [9:0] $end
$scope module dut $end
$var wire 1 # clk $end
$var reg 4 ' count [3:0] $end
$upscope $end
$upscope $end
$upscope $end
$enddefinitions $end
#0
$dumpvars
b0 '
bx &
bx %
b0 $
0#
bx "
bx !
$end
#10
b1 $
b1 '
b11001110 "
b11001110 %
b1 !
b1 &
1#
#20
0#
#30
b10 $
b10 '
b11111100 "
b11111100 %
b10 !
b10 &
1#
#40
0#
#50
b11 $
b11 '
b10110110 "
b10110110 %
b100 !
b100 &
1#
#60
0#
#70
b100 $
b100 '
b11111100 "
b11111100 %
b1000 !
b1000 &
1#
#80
0#
#90
b101 $
b101 '
b10011100 "
b10011100 %
b10000 !
b10000 &
1#
#100
0#
#110
b110 $
b110 '
b11111100 "
b11111100 %
b100000 !
b100000 &
1#
#120
0#
#130
b111 $
b111 '
b11011010 "
b11011010 %
b1000000 !
b1000000 &
1#
#140
0#
#150
b1000 $
b1000 '
b11111100 "
b11111100 %
b10000000 !
b10000000 &
1#
#160
0#
#170
b1001 $
b1001 '
b100000000 !
b100000000 &
1#
#180
0#
#190
b0 $
b0 '
b1000000000 !
b1000000000 &
1#
#200
0#
#210
b1 $
b1 '
b11001110 "
b11001110 %
b1 !
b1 &
1#
#220
0#
#230
b10 $
b10 '
b11111100 "
b11111100 %
b10 !
b10 &
1#
#240
0#
#250
b11 $
b11 '
b10110110 "
b10110110 %
b100 !
b100 &
1#
#260
0#
#270
b100 $
b100 '
b11111100 "
b11111100 %
b1000 !
b1000 &
1#
#280
0#
#290
b101 $
b101 '
b10011100 "
b10011100 %
b10000 !
b10000 &
1#
#300
0#
#310
b110 $
b110 '
b11111100 "
b11111100 %
b100000 !
b100000 &
1#
#320
0#
#330
b111 $
b111 '
b11011010 "
b11011010 %
b1000000 !
b1000000 &
1#
#340
0#
#350
b1000 $
b1000 '
b11111100 "
b11111100 %
b10000000 !
b10000000 &
1#
#360
0#
#370
b1001 $
b1001 '
b100000000 !
b100000000 &
1#
#380
0#
#390
b0 $
b0 '
b1000000000 !
b1000000000 &
1#
#400
0#
#410
b1 $
b1 '
b11001110 "
b11001110 %
b1 !
b1 &
1#
#420
0#
#430
b10 $
b10 '
b11111100 "
b11111100 %
b10 !
b10 &
1#
#440
0#
#450
b11 $
b11 '
b10110110 "
b10110110 %
b100 !
b100 &
1#
#460
0#
#470
b100 $
b100 '
b11111100 "
b11111100 %
b1000 !
b1000 &
1#
#480
0#
#490
b101 $
b101 '
b10011100 "
b10011100 %
b10000 !
b10000 &
1#
#500
0#
#510
b110 $
b110 '
b11111100 "
b11111100 %
b100000 !
b100000 &
1#
#520
0#
#530
b111 $
b111 '
b11011010 "
b11011010 %
b1000000 !
b1000000 &
1#
#540
0#
#550
b1000 $
b1000 '
b11111100 "
b11111100 %
b10000000 !
b10000000 &
1#
#560
0#
#570
b1001 $
b1001 '
b100000000 !
b100000000 &
1#
#580
0#
#590
b0 $
b0 '
b1000000000 !
b1000000000 &
1#
#600
0#
#610
b1 $
b1 '
b11001110 "
b11001110 %
b1 !
b1 &
1#
#620
0#
#630
b10 $
b10 '
b11111100 "
b11111100 %
b10 !
b10 &
1#
#640
0#
#650
b11 $
b11 '
b10110110 "
b10110110 %
b100 !
b100 &
1#
#660
0#
#670
b100 $
b100 '
b11111100 "
b11111100 %
b1000 !
b1000 &
1#
#680
0#
#690
b101 $
b101 '
b10011100 "
b10011100 %
b10000 !
b10000 &
1#
#700
0#
#710
b110 $
b110 '
b11111100 "
b11111100 %
b100000 !
b100000 &
1#
#720
0#
#730
b111 $
b111 '
b11011010 "
b11011010 %
b1000000 !
b1000000 &
1#
#740
0#
#750
b1000 $
b1000 '
b11111100 "
b11111100 %
b10000000 !
b10000000 &
1#
#760
0#
#770
b1001 $
b1001 '
b100000000 !
b100000000 &
1#
#780
0#
#790
b0 $
b0 '
b1000000000 !
b1000000000 &
1#
#800
0#
#810
b1 $
b1 '
b11001110 "
b11001110 %
b1 !
b1 &
1#
#820
0#
#830
b10 $
b10 '
b11111100 "
b11111100 %
b10 !
b10 &
1#
#840
0#
#850
b11 $
b11 '
b10110110 "
b10110110 %
b100 !
b100 &
1#
#860
0#
#870
b100 $
b100 '
b11111100 "
b11111100 %
b1000 !
b1000 &
1#
#880
0#
#890
b101 $
b101 '
b10011100 "
b10011100 %
b10000 !
b10000 &
1#
#900
0#
#910
b110 $
b110 '
b11111100 "
b11111100 %
b100000 !
b100000 &
1#
#920
0#
#930
b111 $
b111 '
b11011010 "
b11011010 %
b1000000 !
b1000000 &
1#
#940
0#
#950
b1000 $
b1000 '
b11111100 "
b11111100 %
b10000000 !
b10000000 &
1#
#960
0#
#970
b1001 $
b1001 '
b100000000 !
b100000000 &
1#
#980
0#
#990
b0 $
b0 '
b1000000000 !
b1000000000 &
1#
#1000
0#
#1010
b1 $
b1 '
b11001110 "
b11001110 %
b1 !
b1 &
1#
#1020
0#
#1030
b10 $
b10 '
b11111100 "
b11111100 %
b10 !
b10 &
1#
#1040
0#
#1050
b11 $
b11 '
b10110110 "
b10110110 %
b100 !
b100 &
1#
#1060
0#
#1070
b100 $
b100 '
b11111100 "
b11111100 %
b1000 !
b1000 &
1#
#1080
0#
#1090
b101 $
b101 '
b10011100 "
b10011100 %
b10000 !
b10000 &
1#
#1100
0#
#1110
b110 $
b110 '
b11111100 "
b11111100 %
b100000 !
b100000 &
1#
#1120
0#
#1130
b111 $
b111 '
b11011010 "
b11011010 %
b1000000 !
b1000000 &
1#
#1140
0#
#1150
b1000 $
b1000 '
b11111100 "
b11111100 %
b10000000 !
b10000000 &
1#
#1160
0#
#1170
b1001 $
b1001 '
b100000000 !
b100000000 &
1#
#1180
0#
#1190
b0 $
b0 '
b1000000000 !
b1000000000 &
1#
#1200
0#
#1210
b1 $
b1 '
b11001110 "
b11001110 %
b1 !
b1 &
1#
#1220
0#
#1230
b10 $
b10 '
b11111100 "
b11111100 %
b10 !
b10 &
1#
#1240
0#
#1250
b11 $
b11 '
b10110110 "
b10110110 %
b100 !
b100 &
1#
#1260
0#
#1270
b100 $
b100 '
b11111100 "
b11111100 %
b1000 !
b1000 &
1#
#1280
0#
#1290
b101 $
b101 '
b10011100 "
b10011100 %
b10000 !
b10000 &
1#
#1300
0#
#1310
b110 $
b110 '
b11111100 "
b11111100 %
b100000 !
b100000 &
1#
#1320
0#
#1330
b111 $
b111 '
b11011010 "
b11011010 %
b1000000 !
b1000000 &
1#
#1340
0#
#1350
b1000 $
b1000 '
b11111100 "
b11111100 %
b10000000 !
b10000000 &
1#
#1360
0#
#1370
b1001 $
b1001 '
b100000000 !
b100000000 &
1#
#1380
0#
#1390
b0 $
b0 '
b1000000000 !
b1000000000 &
1#
#1400
0#
#1410
b1 $
b1 '
b11001110 "
b11001110 %
b1 !
b1 &
1#
#1420
0#
#1430
b10 $
b10 '
b11111100 "
b11111100 %
b10 !
b10 &
1#
#1440
0#
#1450
b11 $
b11 '
b10110110 "
b10110110 %
b100 !
b100 &
1#
#1460
0#
#1470
b100 $
b100 '
b11111100 "
b11111100 %
b1000 !
b1000 &
1#
#1480
0#
#1490
b101 $
b101 '
b10011100 "
b10011100 %
b10000 !
b10000 &
1#
#1500
0#
#1510
b110 $
b110 '
b11111100 "
b11111100 %
b100000 !
b100000 &
1#
#1520
0#
#1530
b111 $
b111 '
b11011010 "
b11011010 %
b1000000 !
b1000000 &
1#
#1540
0#
#1550
b1000 $
b1000 '
b11111100 "
b11111100 %
b10000000 !
b10000000 &
1#
#1560
0#
#1570
b1001 $
b1001 '
b100000000 !
b100000000 &
1#
#1580
0#
#1590
b0 $
b0 '
b1000000000 !
b1000000000 &
1#
#1600
0#
#1610
b1 $
b1 '
b11001110 "
b11001110 %
b1 !
b1 &
1#
#1620
0#
#1630
b10 $
b10 '
b11111100 "
b11111100 %
b10 !
b10 &
1#
#1640
0#
#1650
b11 $
b11 '
b10110110 "
b10110110 %
b100 !
b100 &
1#
#1660
0#
#1670
b100 $
b100 '
b11111100 "
b11111100 %
b1000 !
b1000 &
1#
#1680
0#
#1690
b101 $
b101 '
b10011100 "
b10011100 %
b10000 !
b10000 &
1#
#1700
0#
#1710
b110 $
b110 '
b11111100 "
b11111100 %
b100000 !
b100000 &
1#
#1720
0#
#1730
b111 $
b111 '
b11011010 "
b11011010 %
b1000000 !
b1000000 &
1#
#1740
0#
#1750
b1000 $
b1000 '
b11111100 "
b11111100 %
b10000000 !
b10000000 &
1#
#1760
0#
#1770
b1001 $
b1001 '
b100000000 !
b100000000 &
1#
#1780
0#
#1790
b0 $
b0 '
b1000000000 !
b1000000000 &
1#
#1800
0#
#1810
b1 $
b1 '
b11001110 "
b11001110 %
b1 !
b1 &
1#
#1820
0#
#1830
b10 $
b10 '
b11111100 "
b11111100 %
b10 !
b10 &
1#
#1840
0#
#1850
b11 $
b11 '
b10110110 "
b10110110 %
b100 !
b100 &
1#
#1860
0#
#1870
b100 $
b100 '
b11111100 "
b11111100 %
b1000 !
b1000 &
1#
#1880
0#
#1890
b101 $
b101 '
b10011100 "
b10011100 %
b10000 !
b10000 &
1#
#1900
0#
#1910
b110 $
b110 '
b11111100 "
b11111100 %
b100000 !
b100000 &
1#
#1920
0#
#1930
b111 $
b111 '
b11011010 "
b11011010 %
b1000000 !
b1000000 &
1#
#1940
0#
#1950
b1000 $
b1000 '
b11111100 "
b11111100 %
b10000000 !
b10000000 &
1#
#1960
0#
#1970
b1001 $
b1001 '
b100000000 !
b100000000 &
1#
#1980
0#
#1990
b0 $
b0 '
b1000000000 !
b1000000000 &
1#
